quack_diff/__init__.py
quack_diff/config.py
quack_diff/py.typed
quack_diff/cli/__init__.py
quack_diff/cli/console.py
quack_diff/cli/formatters.py
quack_diff/cli/main.py
quack_diff/cli/commands/__init__.py
quack_diff/cli/commands/attach/__init__.py
quack_diff/cli/commands/diff/__init__.py
quack_diff/cli/commands/schema/__init__.py
quack_diff/core/__init__.py
quack_diff/core/connector.py
quack_diff/core/differ.py
quack_diff/core/query_builder.py
quack_diff/core/adapters/__init__.py
quack_diff/core/adapters/base.py
quack_diff/core/adapters/duckdb.py
quack_diff/core/adapters/snowflake.py
quack_diff-0.0.5.dist-info/METADATA
quack_diff-0.0.5.dist-info/WHEEL
quack_diff-0.0.5.dist-info/entry_points.txt
quack_diff-0.0.5.dist-info/licenses/LICENSE
quack_diff-0.0.5.dist-info/RECORD
