Metadata-Version: 2.4
Name: quack-diff
Version: 0.0.5
Summary: The zero-dependency regression testing tool for modern data warehouses. DuckDB-powered data diffing for Snowflake.
Project-URL: Homepage, https://github.com/matteorenoldi/quack-diff
Project-URL: Repository, https://github.com/matteorenoldi/quack-diff
Project-URL: Issues, https://github.com/matteorenoldi/quack-diff/issues
Author-email: Matteo Renoldi <matteo.renoldi@gmail.com>
License-Expression: MIT
License-File: LICENSE
Keywords: data,data-quality,diff,duckdb,regression-testing,snowflake
Classifier: Development Status :: 3 - Alpha
Classifier: Environment :: Console
Classifier: Intended Audience :: Developers
Classifier: License :: OSI Approved :: MIT License
Classifier: Programming Language :: Python :: 3
Classifier: Programming Language :: Python :: 3.12
Classifier: Programming Language :: Python :: 3.13
Classifier: Topic :: Database
Classifier: Topic :: Software Development :: Testing
Requires-Python: >=3.12
Requires-Dist: duckdb>=1.0.0
Requires-Dist: pydantic-settings>=2.0.0
Requires-Dist: pyyaml>=6.0.0
Requires-Dist: rich>=13.0.0
Requires-Dist: typer[all]>=0.12.0
Provides-Extra: snowflake
Requires-Dist: pandas>=2.0.0; extra == 'snowflake'
Requires-Dist: pyarrow>=14.0.0; extra == 'snowflake'
Requires-Dist: snowflake-connector-python>=3.0.0; extra == 'snowflake'
